odoo/addons/pricelist_cache/README.rst
odoo/addons/pricelist_cache/__init__.py
odoo/addons/pricelist_cache/__manifest__.py
odoo/addons/pricelist_cache/hooks.py
odoo/addons/pricelist_cache/data/demo.xml
odoo/addons/pricelist_cache/data/ir_cron.xml
odoo/addons/pricelist_cache/data/ir_filters_data.xml
odoo/addons/pricelist_cache/data/queue_job.xml
odoo/addons/pricelist_cache/i18n/es.po
odoo/addons/pricelist_cache/i18n/it.po
odoo/addons/pricelist_cache/i18n/pricelist_cache.pot
odoo/addons/pricelist_cache/models/__init__.py
odoo/addons/pricelist_cache/models/product_pricelist.py
odoo/addons/pricelist_cache/models/product_pricelist_cache.py
odoo/addons/pricelist_cache/models/product_pricelist_item.py
odoo/addons/pricelist_cache/models/product_product.py
odoo/addons/pricelist_cache/models/res_partner.py
odoo/addons/pricelist_cache/readme/CONTRIBUTORS.md
odoo/addons/pricelist_cache/readme/CREDITS.md
odoo/addons/pricelist_cache/readme/DESCRIPTION.md
odoo/addons/pricelist_cache/readme/ROADMAP.md
odoo/addons/pricelist_cache/security/ir.model.access.csv
odoo/addons/pricelist_cache/static/description/icon.png
odoo/addons/pricelist_cache/static/description/index.html
odoo/addons/pricelist_cache/tests/__init__.py
odoo/addons/pricelist_cache/tests/common.py
odoo/addons/pricelist_cache/tests/test_methods.py
odoo/addons/pricelist_cache/tests/test_partner_pricelist_cache.py
odoo/addons/pricelist_cache/tests/test_pricelist_cache.py
odoo/addons/pricelist_cache/views/product_pricelist.xml
odoo/addons/pricelist_cache/views/product_pricelist_cache.xml
odoo/addons/pricelist_cache/views/res_partner.xml
odoo/addons/pricelist_cache/wizards/__init__.py
odoo/addons/pricelist_cache/wizards/pricelist_cache_wizard.py
odoo/addons/pricelist_cache/wizards/pricelist_cache_wizard.xml
odoo_addon_pricelist_cache-18.0.1.0.0.4.dist-info/METADATA
odoo_addon_pricelist_cache-18.0.1.0.0.4.dist-info/WHEEL
odoo_addon_pricelist_cache-18.0.1.0.0.4.dist-info/top_level.txt
odoo_addon_pricelist_cache-18.0.1.0.0.4.dist-info/RECORD
